setup.cfg
setup.py
keraflow/__init__.py
keraflow/activations.py
keraflow/callbacks.py
keraflow/constraints.py
keraflow/initializations.py
keraflow/konfig.py
keraflow/models.py
keraflow/objectives.py
keraflow/optimizers.py
keraflow/regularizers.py
keraflow.egg-info/PKG-INFO
keraflow.egg-info/SOURCES.txt
keraflow.egg-info/dependency_links.txt
keraflow.egg-info/requires.txt
keraflow.egg-info/top_level.txt
keraflow/backend/__init__.py
keraflow/backend/common.py
keraflow/backend/tensorflow_backend.py
keraflow/backend/theano_backend.py
keraflow/datasets/__init__.py
keraflow/datasets/common.py
keraflow/datasets/imdb.py
keraflow/datasets/mnist.py
keraflow/datasets/preprocessing.py
keraflow/layers/__init__.py
keraflow/layers/base.py
keraflow/layers/convolution.py
keraflow/layers/core.py
keraflow/layers/embeddings.py
keraflow/layers/recurrent.py
keraflow/layers/wrappers.py
keraflow/utils/__init__.py
keraflow/utils/alias.py
keraflow/utils/exceptions.py
keraflow/utils/generic_utils.py
keraflow/utils/np_utils.py
keraflow/utils/test_utils.py
keraflow/utils/user_input_utils.py