Metadata-Version: 1.1
Name: keraflow
Version: 0.0.1
Summary: Deep Learning for Python
Home-page: https://github.com/ipod825/keraflow
Author: Shih-Ming Wang
Author-email: swang150@ucsc.edu
License: MIT
Download-URL: https://github.com/ipod825/keraflow/tarball/0.0.1
Platform: UNKNOWN
